{
  "analyzedVersion": "e88a060848ee",
  "analyzedCommit": "be6eea91a8bc9ba1b62ff520607d588f06a49d8e",
  "analyzedCommitDate": "2025-08-06T18:03:48.000Z",
  "checks": {
    "array-type": {
      "array": {
        "count": 0,
        "samples": []
      },
      "generic": {
        "count": 13,
        "samples": [
          {
            "file": "website/components/Marp.tsx",
            "line": 50,
            "column": 16,
            "message": "Array type using 'string[]' is forbidden. Use 'Array<string>' instead."
          },
          {
            "file": "website/components/Marp.tsx",
            "line": 95,
            "column": 53,
            "message": "Array type using 'string[]' is forbidden. Use 'Array<string>' instead."
          },
          {
            "file": "website/components/docs/Breadcrumb.tsx",
            "line": 4,
            "column": 16,
            "message": "Array type using 'T[]' is forbidden. Use 'Array<T>' instead."
          },
          {
            "file": "website/components/docs/Navigation.tsx",
            "line": 6,
            "column": 9,
            "message": "Array type using 'string[]' is forbidden. Use 'Array<string>' instead."
          },
          {
            "file": "website/pages/docs/[[...slug]].tsx",
            "line": 30,
            "column": 23,
            "message": "Array type using 'string[]' is forbidden. Use 'Array<string>' instead."
          },
          {
            "file": "website/utils/hooks/useFontFace.tsx",
            "line": 5,
            "column": 44,
            "message": "Array type using 'string[]' is forbidden. Use 'Array<string>' instead."
          },
          {
            "file": "website/utils/hooks/useFontFace.tsx",
            "line": 5,
            "column": 57,
            "message": "Array type using 'string[]' is forbidden. Use 'Array<string>' instead."
          },
          {
            "file": "website/utils/hooks/useFontFace.tsx",
            "line": 16,
            "column": 37,
            "message": "Array type using 'string[]' is forbidden. Use 'Array<string>' instead."
          },
          {
            "file": "website/utils/markdown/parse/image-paragraph-to-figure.ts",
            "line": 47,
            "column": 28,
            "message": "Array type using 'any[]' is forbidden. Use 'Array<any>' instead."
          },
          {
            "file": "website/utils/title.ts",
            "line": 1,
            "column": 44,
            "message": "Array type using 'string[]' is forbidden. Use 'Array<string>' instead."
          }
        ]
      }
    },
    "consistent-generic-constructors": {
      "constructor": {
        "count": 0,
        "samples": []
      },
      "type-annotation": {
        "count": 1,
        "samples": [
          {
            "file": "website/utils/markdown/parse/marp-code-block.ts",
            "line": 6,
            "column": 28,
            "message": "The generic type arguments should be specified as part of the type annotation."
          }
        ]
      }
    },
    "consistent-indexed-object-style": {
      "record": {
        "count": 0,
        "samples": []
      },
      "index-signature": {
        "count": 4,
        "samples": [
          {
            "file": "website/components/docs/Navigation.tsx",
            "line": 5,
            "column": 13,
            "message": "An index signature is preferred over a record."
          },
          {
            "file": "website/components/markdown/Heading.tsx",
            "line": 4,
            "column": 30,
            "message": "An index signature is preferred over a record."
          },
          {
            "file": "website/pages/docs/[[...slug]].tsx",
            "line": 43,
            "column": 20,
            "message": "An index signature is preferred over a record."
          },
          {
            "file": "website/utils/markdown/renderer/index.ts",
            "line": 10,
            "column": 30,
            "message": "An index signature is preferred over a record."
          }
        ]
      }
    },
    "consistent-type-definitions": {
      "interface": {
        "count": 8,
        "samples": [
          {
            "file": "website/components/Button.tsx",
            "line": 4,
            "column": 8,
            "message": "Use `interface` instead of `type`."
          },
          {
            "file": "website/components/CodeBlock.tsx",
            "line": 24,
            "column": 8,
            "message": "Use `interface` instead of `type`."
          },
          {
            "file": "website/components/Marp.tsx",
            "line": 16,
            "column": 8,
            "message": "Use `interface` instead of `type`."
          },
          {
            "file": "website/components/blog/BlogHeader.tsx",
            "line": 4,
            "column": 8,
            "message": "Use `interface` instead of `type`."
          },
          {
            "file": "website/components/docs/Breadcrumb.tsx",
            "line": 3,
            "column": 8,
            "message": "Use `interface` instead of `type`."
          },
          {
            "file": "website/components/docs/Navigation.tsx",
            "line": 4,
            "column": 8,
            "message": "Use `interface` instead of `type`."
          },
          {
            "file": "website/components/markdown/Image.tsx",
            "line": 1,
            "column": 8,
            "message": "Use `interface` instead of `type`."
          },
          {
            "file": "website/components/top/Description.tsx",
            "line": 8,
            "column": 8,
            "message": "Use `interface` instead of `type`."
          }
        ]
      },
      "type": {
        "count": 2,
        "samples": [
          {
            "file": "website/global.d.ts",
            "line": 4,
            "column": 3,
            "message": "Use `type` instead of `interface`."
          },
          {
            "file": "website/utils/hooks/useFontFace.tsx",
            "line": 3,
            "column": 1,
            "message": "Use `type` instead of `interface`."
          }
        ]
      }
    },
    "consistent-type-imports": {
      "type-imports": {
        "count": 19,
        "samples": [
          {
            "file": "website/components/Button.tsx",
            "line": 2,
            "column": 1,
            "message": "All imports in the declaration are only used as types. Use `import type`."
          },
          {
            "file": "website/components/CodeBlock.tsx",
            "line": 9,
            "column": 1,
            "message": "Imports MouseEvent are only used as type."
          },
          {
            "file": "website/components/Marp.tsx",
            "line": 3,
            "column": 1,
            "message": "Imports Plugin are only used as type."
          },
          {
            "file": "website/components/docs/Layout.tsx",
            "line": 3,
            "column": 1,
            "message": "All imports in the declaration are only used as types. Use `import type`."
          },
          {
            "file": "website/components/docs/layouts/Desktop.tsx",
            "line": 9,
            "column": 1,
            "message": "All imports in the declaration are only used as types. Use `import type`."
          },
          {
            "file": "website/components/top/Description.tsx",
            "line": 6,
            "column": 1,
            "message": "Imports RenderedMarp are only used as type."
          },
          {
            "file": "website/pages/blog/[slug].tsx",
            "line": 2,
            "column": 1,
            "message": "All imports in the declaration are only used as types. Use `import type`."
          },
          {
            "file": "website/pages/index.tsx",
            "line": 1,
            "column": 1,
            "message": "All imports in the declaration are only used as types. Use `import type`."
          },
          {
            "file": "website/utils/markdown/parse/marp-code-block.ts",
            "line": 3,
            "column": 1,
            "message": "Imports RenderedMarp are only used as type."
          },
          {
            "file": "website/utils/markdown/renderer/index.ts",
            "line": 2,
            "column": 1,
            "message": "Imports Options are only used as type."
          }
        ]
      },
      "no-type-imports": {
        "count": 3,
        "samples": [
          {
            "file": "website/components/Marp.tsx",
            "line": 6,
            "column": 1,
            "message": "Use an `import` instead of an `import type`."
          },
          {
            "file": "website/components/top/Features.tsx",
            "line": 10,
            "column": 1,
            "message": "Use an `import` instead of an `import type`."
          },
          {
            "file": "website/utils/markdown/parse/marp-code-block.ts",
            "line": 1,
            "column": 1,
            "message": "Use an `import` instead of an `import type`."
          }
        ]
      }
    },
    "func-style": {
      "expression": {
        "count": 0,
        "samples": []
      },
      "declaration": {
        "count": 75,
        "samples": [
          {
            "file": "website/components/Button.tsx",
            "line": 12,
            "column": 14,
            "message": "Expected a function declaration."
          },
          {
            "file": "website/components/Marp.tsx",
            "line": 88,
            "column": 14,
            "message": "Expected a function declaration."
          },
          {
            "file": "website/components/docs/layouts/Desktop.tsx",
            "line": 12,
            "column": 14,
            "message": "Expected a function declaration."
          },
          {
            "file": "website/components/markdown/Heading.tsx",
            "line": 32,
            "column": 14,
            "message": "Expected a function declaration."
          },
          {
            "file": "website/components/markdown/Pre.tsx",
            "line": 17,
            "column": 14,
            "message": "Expected a function declaration."
          },
          {
            "file": "website/pages/404.tsx",
            "line": 5,
            "column": 7,
            "message": "Expected a function declaration."
          },
          {
            "file": "website/pages/blog/[slug].tsx",
            "line": 14,
            "column": 14,
            "message": "Expected a function declaration."
          },
          {
            "file": "website/postcss.config.js",
            "line": 4,
            "column": 7,
            "message": "Expected a function declaration."
          },
          {
            "file": "website/utils/markdown/index.tsx",
            "line": 8,
            "column": 14,
            "message": "Expected a function declaration."
          },
          {
            "file": "website/utils/url.ts",
            "line": 1,
            "column": 14,
            "message": "Expected a function declaration."
          }
        ]
      }
    },
    "import-export-preference": {
      "named": {
        "count": 7,
        "samples": [
          {
            "file": "website/pages/404.tsx",
            "line": 40,
            "column": 8,
            "message": "Prefer named exports"
          },
          {
            "file": "website/pages/_app.tsx",
            "line": 73,
            "column": 8,
            "message": "Prefer named exports"
          },
          {
            "file": "website/pages/_document.tsx",
            "line": 26,
            "column": 8,
            "message": "Prefer named exports"
          },
          {
            "file": "website/pages/blog.tsx",
            "line": 202,
            "column": 8,
            "message": "Prefer named exports"
          },
          {
            "file": "website/pages/blog/[slug].tsx",
            "line": 70,
            "column": 8,
            "message": "Prefer named exports"
          },
          {
            "file": "website/pages/docs/[[...slug]].tsx",
            "line": 69,
            "column": 8,
            "message": "Prefer named exports"
          },
          {
            "file": "website/pages/index.tsx",
            "line": 59,
            "column": 8,
            "message": "Prefer named exports"
          }
        ]
      },
      "default": {
        "count": 17,
        "samples": [
          {
            "file": "website/components/Footer.tsx",
            "line": 3,
            "column": 1,
            "message": "Prefer default export on a file with single export."
          },
          {
            "file": "website/components/Title.tsx",
            "line": 2,
            "column": 1,
            "message": "Prefer default export on a file with single export."
          },
          {
            "file": "website/components/docs/layouts/Desktop.tsx",
            "line": 12,
            "column": 1,
            "message": "Prefer default export on a file with single export."
          },
          {
            "file": "website/components/docs/layouts/Mobile.tsx",
            "line": 87,
            "column": 1,
            "message": "Prefer default export on a file with single export."
          },
          {
            "file": "website/components/top/Features.tsx",
            "line": 287,
            "column": 1,
            "message": "Prefer default export on a file with single export."
          },
          {
            "file": "website/components/top/Hero.tsx",
            "line": 7,
            "column": 1,
            "message": "Prefer default export on a file with single export."
          },
          {
            "file": "website/utils/markdown/parse/index.ts",
            "line": 11,
            "column": 1,
            "message": "Prefer default export on a file with single export."
          },
          {
            "file": "website/utils/markdown/parse/marp-code-block.ts",
            "line": 5,
            "column": 1,
            "message": "Prefer default export on a file with single export."
          },
          {
            "file": "website/utils/markdown/renderer/sanitize.ts",
            "line": 3,
            "column": 1,
            "message": "Prefer default export on a file with single export."
          },
          {
            "file": "website/utils/url.ts",
            "line": 1,
            "column": 1,
            "message": "Prefer default export on a file with single export."
          }
        ]
      }
    },
    "indent": {
      "2-space": {
        "count": 0,
        "samples": []
      },
      "4-space": {
        "count": 48,
        "samples": [
          {
            "file": ".eslintrc.js",
            "line": 5,
            "column": 1,
            "message": "Expected 4-space indentation, but file uses 2-space indentation."
          },
          {
            "file": "website/components/Footer.tsx",
            "line": 4,
            "column": 1,
            "message": "Expected 4-space indentation, but file uses 2-space indentation."
          },
          {
            "file": "website/components/Title.tsx",
            "line": 3,
            "column": 1,
            "message": "Expected 4-space indentation, but file uses 2-space indentation."
          },
          {
            "file": "website/components/docs/layouts/Desktop.tsx",
            "line": 2,
            "column": 1,
            "message": "Expected 4-space indentation, but file uses 2-space indentation."
          },
          {
            "file": "website/components/markdown/Pre.tsx",
            "line": 4,
            "column": 1,
            "message": "Expected 4-space indentation, but file uses 2-space indentation."
          },
          {
            "file": "website/css/plugin-rem.js",
            "line": 8,
            "column": 1,
            "message": "Expected 4-space indentation, but file uses 2-space indentation."
          },
          {
            "file": "website/pages/_document.tsx",
            "line": 4,
            "column": 1,
            "message": "Expected 4-space indentation, but file uses 2-space indentation."
          },
          {
            "file": "website/tailwind.config.js",
            "line": 5,
            "column": 1,
            "message": "Expected 4-space indentation, but file uses 2-space indentation."
          },
          {
            "file": "website/utils/markdown/parse/index.ts",
            "line": 12,
            "column": 1,
            "message": "Expected 4-space indentation, but file uses 2-space indentation."
          },
          {
            "file": "website/utils/url.ts",
            "line": 2,
            "column": 1,
            "message": "Expected 4-space indentation, but file uses 2-space indentation."
          }
        ]
      },
      "tab": {
        "count": 48,
        "samples": [
          {
            "file": ".eslintrc.js",
            "line": 5,
            "column": 1,
            "message": "Expected tabs for indentation, but found spaces."
          },
          {
            "file": "website/components/Footer.tsx",
            "line": 4,
            "column": 1,
            "message": "Expected tabs for indentation, but found spaces."
          },
          {
            "file": "website/components/Title.tsx",
            "line": 3,
            "column": 1,
            "message": "Expected tabs for indentation, but found spaces."
          },
          {
            "file": "website/components/docs/layouts/Desktop.tsx",
            "line": 2,
            "column": 1,
            "message": "Expected tabs for indentation, but found spaces."
          },
          {
            "file": "website/components/markdown/Pre.tsx",
            "line": 4,
            "column": 1,
            "message": "Expected tabs for indentation, but found spaces."
          },
          {
            "file": "website/css/plugin-rem.js",
            "line": 8,
            "column": 1,
            "message": "Expected tabs for indentation, but found spaces."
          },
          {
            "file": "website/pages/_document.tsx",
            "line": 4,
            "column": 1,
            "message": "Expected tabs for indentation, but found spaces."
          },
          {
            "file": "website/tailwind.config.js",
            "line": 5,
            "column": 1,
            "message": "Expected tabs for indentation, but found spaces."
          },
          {
            "file": "website/utils/markdown/parse/index.ts",
            "line": 12,
            "column": 1,
            "message": "Expected tabs for indentation, but found spaces."
          },
          {
            "file": "website/utils/url.ts",
            "line": 2,
            "column": 1,
            "message": "Expected tabs for indentation, but found spaces."
          }
        ]
      }
    },
    "quotes": {
      "double": {
        "count": 475,
        "samples": [
          {
            "file": ".eslintrc.js",
            "line": 1,
            "column": 22,
            "message": "Strings must use doublequote."
          },
          {
            "file": "website/components/CodeBlock.tsx",
            "line": 9,
            "column": 46,
            "message": "Strings must use doublequote."
          },
          {
            "file": "website/components/Marp.tsx",
            "line": 19,
            "column": 32,
            "message": "Strings must use doublequote."
          },
          {
            "file": "website/components/docs/layouts/Desktop.tsx",
            "line": 90,
            "column": 33,
            "message": "Strings must use doublequote."
          },
          {
            "file": "website/components/top/Description.tsx",
            "line": 5,
            "column": 27,
            "message": "Strings must use doublequote."
          },
          {
            "file": "website/next.config.js",
            "line": 9,
            "column": 44,
            "message": "Strings must use doublequote."
          },
          {
            "file": "website/pages/blog.tsx",
            "line": 95,
            "column": 27,
            "message": "Strings must use doublequote."
          },
          {
            "file": "website/postcss.config.js",
            "line": 25,
            "column": 14,
            "message": "Strings must use doublequote."
          },
          {
            "file": "website/utils/date.ts",
            "line": 33,
            "column": 5,
            "message": "Strings must use doublequote."
          },
          {
            "file": "website/utils/title.ts",
            "line": 7,
            "column": 10,
            "message": "Strings must use doublequote."
          }
        ]
      },
      "single": {
        "count": 3,
        "samples": [
          {
            "file": "website/components/docs/layouts/Desktop.tsx",
            "line": 91,
            "column": 28,
            "message": "Strings must use singlequote."
          },
          {
            "file": "website/components/docs/layouts/Desktop.tsx",
            "line": 92,
            "column": 30,
            "message": "Strings must use singlequote."
          },
          {
            "file": "website/pages/blog.tsx",
            "line": 95,
            "column": 27,
            "message": "Strings must use singlequote."
          }
        ]
      }
    },
    "semi": {
      "always": {
        "count": 568,
        "samples": [
          {
            "file": ".eslintrc.js",
            "line": 1,
            "column": 29,
            "message": "Missing semicolon."
          },
          {
            "file": "website/components/Layout.tsx",
            "line": 34,
            "column": 49,
            "message": "Missing semicolon."
          },
          {
            "file": "website/components/docs/Layout.tsx",
            "line": 1,
            "column": 53,
            "message": "Missing semicolon."
          },
          {
            "file": "website/components/docs/layouts/Mobile.tsx",
            "line": 2,
            "column": 71,
            "message": "Missing semicolon."
          },
          {
            "file": "website/components/markdown/Heading.tsx",
            "line": 43,
            "column": 2,
            "message": "Missing semicolon."
          },
          {
            "file": "website/css/plugin-rem.js",
            "line": 27,
            "column": 30,
            "message": "Missing semicolon."
          },
          {
            "file": "website/pages/blog.tsx",
            "line": 11,
            "column": 67,
            "message": "Missing semicolon."
          },
          {
            "file": "website/pages/index.tsx",
            "line": 2,
            "column": 43,
            "message": "Missing semicolon."
          },
          {
            "file": "website/utils/markdown/index.tsx",
            "line": 6,
            "column": 65,
            "message": "Missing semicolon."
          },
          {
            "file": "website/utils/url.ts",
            "line": 2,
            "column": 46,
            "message": "Missing semicolon."
          }
        ]
      },
      "never": {
        "count": 0,
        "samples": []
      }
    }
  }
}
